xarray_adios2/__init__.py
xarray_adios2/_version.py
xarray_adios2/_version.pyi
xarray_adios2/adios2array.py
xarray_adios2/adios2backend.py
xarray_adios2/adios2store.py
xarray_adios2/py.typed
xarray_adios2-0.1.0a3.dist-info/licenses/LICENSE
xarray_adios2-0.1.0a3.dist-info/METADATA
xarray_adios2-0.1.0a3.dist-info/WHEEL
xarray_adios2-0.1.0a3.dist-info/entry_points.txt
xarray_adios2-0.1.0a3.dist-info/top_level.txt
xarray_adios2-0.1.0a3.dist-info/RECORD
