Metadata-Version: 2.4
Name: xarray-adios2
Version: 0.1.0a3
Summary: An xarray backend to read/write ADIOS2 files/streams.
Author-email: Kai Germaschewski <kai.germaschewski@gmail.com>
License: 
Project-URL: Homepage, https://github.com/unh-hpc/xarray-adios2
Project-URL: Bug Tracker, https://github.com/unh-hpc/xarray-adios2/issues
Project-URL: Discussions, https://github.com/unh-hpc/xarray-adios2/discussions
Project-URL: Changelog, https://github.com/unh-hpc/xarray-adios2/releases
Classifier: Development Status :: 1 - Planning
Classifier: Intended Audience :: Science/Research
Classifier: Intended Audience :: Developers
Classifier: License :: OSI Approved :: Apache Software License
Classifier: Operating System :: OS Independent
Classifier: Programming Language :: Python
Classifier: Programming Language :: Python :: 3
Classifier: Programming Language :: Python :: 3 :: Only
Classifier: Programming Language :: Python :: 3.10
Classifier: Programming Language :: Python :: 3.11
Classifier: Programming Language :: Python :: 3.12
Classifier: Programming Language :: Python :: 3.13
Classifier: Topic :: Scientific/Engineering
Classifier: Typing :: Typed
Requires-Python: >=3.10
License-File: LICENSE
Requires-Dist: adios2py
Requires-Dist: xarray<2025.07
Requires-Dist: typing-extensions
Provides-Extra: test
Requires-Dist: pytest>=6; extra == "test"
Requires-Dist: pytest-cov>=3; extra == "test"
Provides-Extra: dev
Requires-Dist: pytest>=6; extra == "dev"
Requires-Dist: pytest-cov>=3; extra == "dev"
Provides-Extra: docs
Requires-Dist: sphinx>=7.0; extra == "docs"
Requires-Dist: myst_parser>=0.13; extra == "docs"
Requires-Dist: sphinx_copybutton; extra == "docs"
Requires-Dist: sphinx_autodoc_typehints; extra == "docs"
Requires-Dist: furo>=2023.08.17; extra == "docs"
Dynamic: license-file
